MANIFEST.in
README.md
requirements.txt
setup.cfg
setup.py
lwrf/__init__.py
lwrf/v1/__init__.py
lwrf/v1/hub.py
lwrf/v1/light.py
python_lwrf.egg-info/PKG-INFO
python_lwrf.egg-info/SOURCES.txt
python_lwrf.egg-info/dependency_links.txt
python_lwrf.egg-info/top_level.txt